Workbook

Sheet Dashboard
A1: codencode · Budget Tracker
A2: ✦ Python & ML Fundamentals Academy · Johor Bahru, Malaysia ✦
A4: TOTAL INCOME (MYR) | D4: TOTAL EXPENSES (MYR) | G4: NET BALANCE (MYR) | J4: BUDGET USED
A5: =E18 -> 0 | D5: =K18 -> 0 | G5: =A5-D5 -> 0 | J5: =IF(A5=0,0,D5/A5) -> 0
A10: 🟢 INCOME SUMMARY | G10: 🔴 EXPENSE SUMMARY
A11: Category | B11: May 2026 | C11: Sep 2026 | D11: Nov 2026 | E11: Total | G11: Category | H11: May 2026 | I11: Sep 2026 | J11: Nov 2026 | K11: Total
A12: Course Fees | B12: =Income!B4 -> 0 | C12: =Income!C4 -> 0 | D12: =Income!E4 -> 0 | E12: =SUM(B12:D12) -> 0 | G12: Venue Rental | H12: =Expenses!B4 -> 0 | I12: =Expenses!C4 -> 0 | J12: =Expenses!D4 -> 0 | K12: =SUM(H12:J12) -> 0
A13: Registration Fees | B13: =Income!B5 -> 0 | C13: =Income!C5 -> 0 | D13: =Income!E5 -> 0 | E13: =SUM(B13:D13) -> 0 | G13: Instructor Fees | H13: =Expenses!B5 -> 0 | I13: =Expenses!C5 -> 0 | J13: =Expenses!D5 -> 0 | K13: =SUM(H13:J13) -> 0
A14: Corporate / B2B | B14: =Income!B6 -> 0 | C14: =Income!C6 -> 0 | D14: =Income!E6 -> 0 | E14: =SUM(B14:D14) -> 0 | G14: Marketing | H14: =Expenses!B6 -> 0 | I14: =Expenses!C6 -> 0 | J14: =Expenses!D6 -> 0 | K14: =SUM(H14:J14) -> 0
A15: Sponsorships | B15: =Income!B7 -> 0 | C15: =Income!C7 -> 0 | D15: =Income!E7 -> 0 | E15: =SUM(B15:D15) -> 0 | G15: Materials | H15: =Expenses!B7 -> 0 | I15: =Expenses!C7 -> 0 | J15: =Expenses!D7 -> 0 | K15: =SUM(H15:J15) -> 0
A16: Merchandise | B16: =Income!B8 -> 0 | C16: =Income!C8 -> 0 | D16: =Income!E8 -> 0 | E16: =SUM(B16:D16) -> 0 | G16: Platform / SaaS | H16: =Expenses!B8 -> 0 | I16: =Expenses!C8 -> 0 | J16: =Expenses!D8 -> 0 | K16: =SUM(H16:J16) -> 0
A17: Other Income | B17: =Income!B9 -> 0 | C17: =Income!C9 -> 0 | D17: =Income!E9 -> 0 | E17: =SUM(B17:D17) -> 0 | G17: Admin & Misc | H17: =Expenses!B9 -> 0 | I17: =Expenses!C9 -> 0 | J17: =Expenses!D9 -> 0 | K17: =SUM(H17:J17) -> 0
A18: TOTAL | B18: =SUM(B12:B17) -> 0 | C18: =SUM(C12:C17) -> 0 | D18: =SUM(D12:D17) -> 0 | E18: =SUM(B18:D18) -> 0 | G18: TOTAL | H18: =SUM(H12:H17) -> 0 | I18: =SUM(I12:I17) -> 0 | J18: =SUM(J12:J17) -> 0 | K18: =SUM(H18:J18) -> 0

Sheet Income
A1: INCOME TRACKER
A2: Track all revenue streams across cohorts · Enter values in blue cells
A3: Category | B3: May 2026 (MYR) | C3: Sep 2026 (MYR) | D3: Nov 2026 (MYR) | E3: Nov 2026 (MYR) | F3: Total (MYR) | G3: Notes
A4: Course Fees | B4: 0 | C4: 0 | E4: 0 | F4: =SUM(B4:E4) -> 0 | G4: Python Fundamentals – RM500/pax
A5: Registration Fees | B5: 0 | C5: 0 | E5: 0 | F5: =SUM(B5:E5) -> 0 | G5: One-time admin fee per student
A6: Corporate / B2B | B6: 0 | C6: 0 | E6: 0 | F6: =SUM(B6:E6) -> 0 | G6: Custom training packages
A7: Sponsorships | B7: 0 | C7: 0 | E7: 0 | F7: =SUM(B7:E7) -> 0 | G7: Tech company sponsorships
A8: Merchandise | B8: 0 | C8: 0 | E8: 0 | F8: =SUM(B8:E8) -> 0 | G8: Branded notebooks, tees, etc.
A9: Other Income | B9: 0 | C9: 0 | E9: 0 | F9: =SUM(B9:E9) -> 0 | G9: Grants, competitions, misc
A10: TOTAL INCOME | B10: =SUM(B4:B9) -> 0 | C10: =SUM(C4:C9) -> 0 | E10: =SUM(E4:E9) -> 0 | F10: =SUM(F4:F9) -> 0

Sheet Expenses
A1: EXPENSE TRACKER
A2: Track all operating costs across cohorts · Enter values in blue cells
A3: Category | B3: May 2026 (MYR) | C3: Sep 2026 (MYR) | D3: Nov 2026 (MYR) | E3: Total (MYR) | F3: Notes | I3: Google Review - RM2 / Review Admin - RM 260 + Posters(RM10)
A4: Venue Rental | B4: 0 | C4: 0 | D4: 0 | E4: 0 | F4: Co-working / classroom space
A5: Instructor Fees | B5: 0 | C5: 0 | D5: 0 | E5: 0 | F5: Lead instructor + TA stipend
A6: Marketing | B6: 0 | C6: 0 | D6: 0 | E6: 0 | F6: Meta Ads, XHS boosts, printing
A7: Materials | B7: 0 | C7: 0 | D7: 0 | E7: 0 | F7: Workbooks, USB drives, kits
A8: Platform / SaaS | B8: 0 | C8: 0 | D8: 0 | E8: 0 | F8: Zoom, Canva Pro, GitHub, Notion
A9: Admin & Misc | B9: 0 | C9: 0 | D9: 0 | E9: 0 | F9: Transport, meals, contingency
A10: TOTAL EXPENSES | B10: =SUM(B4:B9) -> 0 | C10: =SUM(C4:C9) -> 0 | D10: =SUM(D4:D9) -> 0 | E10: =SUM(E4:E9) -> 0

Sheet Transactions
A1: TRANSACTION LOG
A2: Date | B2: Type | C2: Category | D2: Cohort | E2: Description | F2: Amount (MYR) | G2: Reference | H2: Status
A3: 46094 | B3: Expense | C3: Google Business | D3: May 2026 | E3: 6 Google Reviews | F3: 14 | G3: TNG | H3: Paid
A4: 46097 | B4: Expense | C4: Company Registration | E4: Company Registration | F4: 70 | G4: MAE | H4: Paid
F35: =SUM(F3:F34) -> 84

Sheet P&L Summary
A1: PROFIT & LOSS SUMMARY
A2: Auto-calculated from Income & Expenses sheets
A3: Line Item | B3: May 2026 | C3: Sep 2026 | D3: Nov 2026 | E3: TOTAL
A4: Total Revenue | B4: =Income!B10 -> 0 | C4: =Income!C10 -> 0 | D4: =Income!E10 -> 0 | E4: =SUM(B4:D4) -> 0
A5: Total Expenses | B5: =Expenses!B10 -> 0 | C5: =Expenses!C10 -> 0 | D5: =Expenses!D10 -> 0 | E5: =SUM(B5:D5) -> 0
A6: Gross Profit | B6: =B4-B5 -> 0 | C6: =C4-C5 -> 0 | D6: =D4-D5 -> 0 | E6: =SUM(B6:D6) -> 0
A7: Profit Margin | B7: =IF(B4=0,0,B6/B4) -> 0 | C7: =IF(C4=0,0,C6/C4) -> 0 | D7: =IF(D4=0,0,D6/D4) -> 0 | E7: =IF(E4=0,0,E6/E4) -> 0
